{"batchcomplete": "", "query": {"pages": {"5157": {"pageid": 5157, "ns": 0, "title": "Nancy", "revisions": [{"slots": {"main": {"contentmodel": "wikitext", "contentformat": "text/x-wiki", "*": ": ''This article is about Rachel's coworker at Ralph Lauren. For Monica and Chandler's realtor, see [[Nancy (realtor)]]''\n{{Character\n| | character name = Nancy\n| image = [[File:Nancy.png|thumb|328px]]\n| ep = [[The One Where Rachel Smokes]]\n| number = 1\n| actor = [[Megan Ward]]\n| name = Nancy\n| gender = Female\n| nickname = Smokey Smokison <small>(by [[Rachel Greene|Rachel]])</small>\n| occ = Executive at Ralph Lauren\n}}\n\n'''Nancy''' is [[Rachel Greene|Rachel]]'s colleague at Ralph Lauren, portrayed by [[Megan Ward]]. She is shown to be a smoker and close with her boss, [[Kim]].\n[[Category:Friends Characters]]\n[[Category:Season 5 Characters]]\n[[Category:One Appearance Only]]\n[[Category:Females]]\n[[Category:Rachel's Work]]\n[[Category:Characters]]"}}}]}}}}